tartiflette_request_sa_session/__init__.py
tartiflette_request_sa_session/database.py
tartiflette_request_sa_session/middleware.py
tartiflette_request_sa_session/request_context_hooks.py
tartiflette_request_sqlalchemy_session-1.0.0.dist-info/LICENSE
tartiflette_request_sqlalchemy_session-1.0.0.dist-info/METADATA
tartiflette_request_sqlalchemy_session-1.0.0.dist-info/WHEEL
tartiflette_request_sqlalchemy_session-1.0.0.dist-info/top_level.txt
tartiflette_request_sqlalchemy_session-1.0.0.dist-info/RECORD
