Metadata-Version: 2.1
Name: tartiflette-request-sqlalchemy-session
Version: 1.0.0
Summary: Middleware for the [tartiflette](https://tartiflette.io/) GraphQL server implementation to have a SQLAlchemy Session generated on each server request which is then injected into the resolver context.
Home-page: https://github.com/daveoconnor/tartiflette-request-sqlalchemy-session
Author: Dave O'Connor
Author-email: github@dead-pixels.org
License: UNKNOWN
Platform: UNKNOWN
Classifier: Programming Language :: Python :: 3
Classifier: License :: OSI Approved :: MIT License
Classifier: Operating System :: OS Independent
Requires-Python: >=3.8
Requires-Dist: tartiflette-middleware (>=1.0)
Requires-Dist: SQLAlchemy (>=1.3)
Provides-Extra: psycopg
Requires-Dist: psycopg2-binary (>=2.8) ; extra == 'psycopg'
